slackflylog/__init__.py
slackflylog/constants.py
slackflylog/setup.py
slackflylog/agent/__init__.py
slackflylog/agent/agent.py
slackflylog/agent/log.py
slackflylog/agent/utils.py
slackflylog/agent/backends/__init__.py
slackflylog/agent/backends/send_slack.py
slackflylog/api/__init__.py
slackflylog/api/client.py
slackflylog/api/log_handler.py
slackflylog-3.0.8.dist-info/LICENSE
slackflylog-3.0.8.dist-info/METADATA
slackflylog-3.0.8.dist-info/WHEEL
slackflylog-3.0.8.dist-info/top_level.txt
slackflylog-3.0.8.dist-info/RECORD
